[{"currentRank":1,"team":"Malmöns Pensionat","matches":"11","match_points":"45-21","team_points":"17"},{"currentRank":2,"team":"Tyréns","matches":"11","match_points":"41-25","team_points":"14"},{"currentRank":3,"team":"Bergelin Bros","matches":"11","match_points":"39-27","team_points":"14"},{"currentRank":4,"team":"Skruvarna","matches":"11","match_points":"34-32","team_points":"13"},{"currentRank":5,"team":"Harås Byggvaror","matches":"11","match_points":"36-30","team_points":"11"},{"currentRank":6,"team":"Tennis-spelarna","matches":"11","match_points":"34-32","team_points":"11"},{"currentRank":7,"team":"Tennis-spelarna","matches":"11","match_points":"34-32","team_points":"11"},{"currentRank":8,"team":"Nols TK","matches":"11","match_points":"35-31","team_points":"10"},{"currentRank":9,"team":"Tennispolarna","matches":"11","match_points":"32-34","team_points":"10"},{"currentRank":10,"team":"Stannum Taxi","matches":"11","match_points":"28-38","team_points":"9"},{"currentRank":11,"team":"Chalmers R2","matches":"11","match_points":"26-40","team_points":"8"},{"currentRank":12,"team":"Forbo Flooring","matches":"11","match_points":"24-42","team_points":"8"},{"currentRank":13,"team":"Bilia","matches":"11","match_points":"22-44","team_points":"7"}]
